edgefxn/__init__.py
edgefxn/version.py
edgefxn-0.0.1.dist-info/LICENSE
edgefxn-0.0.1.dist-info/METADATA
edgefxn-0.0.1.dist-info/WHEEL
edgefxn-0.0.1.dist-info/top_level.txt
edgefxn-0.0.1.dist-info/RECORD
